discoecs
