Metadata-Version: 2.1
Name: discoecs
Version: 2.2.2
Summary: Easy to setup AWS ECS autodiscovery for Prometheus
Home-page: https://github.com/bindreturn/discoecs
Author: bindreturn
Author-email: bindreturn@protonmail.ch
License: UNKNOWN
Platform: UNKNOWN
Classifier: License :: OSI Approved :: MIT License
Classifier: Operating System :: OS Independent
Classifier: Programming Language :: Python :: 3
